setup.cfg
setup.py
turbine_cli/__init__.py
turbine_cli/cli.py
turbine_cli.egg-info/PKG-INFO
turbine_cli.egg-info/SOURCES.txt
turbine_cli.egg-info/dependency_links.txt
turbine_cli.egg-info/entry_points.txt
turbine_cli.egg-info/not-zip-safe
turbine_cli.egg-info/requires.txt
turbine_cli.egg-info/top_level.txt
turbine_cli/clean/__init__.py
turbine_cli/clean/command.py
turbine_cli/create/__init__.py
turbine_cli/create/command.py
turbine_cli/package/__init__.py
turbine_cli/package/build.py
turbine_cli/package/upload.py