Metadata-Version: 1.1
Name: turbine-cli
Version: 0.0.2
Summary: Turbine scaffolding and utility package
Home-page: https://github.com/dmikov/turbine-cli
Author: Dmitriy Krasnikov
Author-email: dmitriy.krasnikov@swimlane.com
License: BSD
Platform: any
Classifier: Development Status :: 4 - Beta
Classifier: Environment :: Console
Classifier: Intended Audience :: Developers
Classifier: License :: OSI Approved :: BSD License
Classifier: Operating System :: POSIX
Classifier: Operating System :: MacOS
Classifier: Operating System :: Unix
Classifier: Operating System :: Microsoft :: Windows
Classifier: Programming Language :: Python
Classifier: Programming Language :: Python :: 2
Classifier: Programming Language :: Python :: 3
Classifier: Topic :: Software Development :: Libraries :: Python Modules
